Metadata-Version: 2.1
Name: telnet2
Version: 1.1.2
Summary: simple telnet module
Home-page: https://github.com/AlaBouali/telnet2
Author: AlaBouali
Author-email: trap.leader.123@gmail.com
License: MIT License
Platform: UNKNOWN
Classifier: Programming Language :: Python
Classifier: License :: OSI Approved :: MIT License 
Requires-Python: >=2.7
